mks_servo_rs485/__init__.py
mks_servo_rs485/scan.py
mks_servo_rs485/servo.py
mks_servo_rs485-0.3.0.dist-info/LICENSE
mks_servo_rs485-0.3.0.dist-info/METADATA
mks_servo_rs485-0.3.0.dist-info/WHEEL
mks_servo_rs485-0.3.0.dist-info/top_level.txt
mks_servo_rs485-0.3.0.dist-info/RECORD
